topsis_rupanshijain_102017010
